<annotation>
	<folder>collectedimages</folder>
	<filename>hello.ae62cced-82cb-11ed-92c1-086ac5570a70.jpg</filename>
	<path>C:\Users\33771\Desktop\VS Window\IA\AppSleep\RealTimeObjectDetection\Tensorflow\workspace\images\collectedimages\hello.ae62cced-82cb-11ed-92c1-086ac5570a70.jpg</path>
	<source>
		<database>Unknown</database>
	</source>
	<size>
		<width>640</width>
		<height>480</height>
		<depth>3</depth>
	</size>
	<segmented>0</segmented>
	<object>
		<name>Hello</name>
		<pose>Unspecified</pose>
		<truncated>0</truncated>
		<difficult>0</difficult>
		<bndbox>
			<xmin>284</xmin>
			<ymin>120</ymin>
			<xmax>611</xmax>
			<ymax>461</ymax>
		</bndbox>
	</object>
</annotation>
